publishsub/__init__.py
publishsub-1.0.0.dist-info/licenses/LICENSE
publishsub-1.0.0.dist-info/METADATA
publishsub-1.0.0.dist-info/WHEEL
publishsub-1.0.0.dist-info/top_level.txt
publishsub-1.0.0.dist-info/RECORD
